MANIFEST.in
README.rst
setup.py
mongomodel/__init__.py
mongomodel/conn.py
mongomodel/meta.py
mongomodel/model.py
mongomodel/tests/__init__.py
mongomodel/tests/test_conn.py
mongomodel/tests/test_model.py
txMongoModel.egg-info/PKG-INFO
txMongoModel.egg-info/SOURCES.txt
txMongoModel.egg-info/dependency_links.txt
txMongoModel.egg-info/requires.txt
txMongoModel.egg-info/top_level.txt