Metadata-Version: 1.0
Name: txMongoModel
Version: 0.0.3
Summary: A data model wrapper for async MongoDB
Home-page: http://github.com/oubiwann/txMongoModel
Author: Duncan McGreggor
Author-email: duncan@cogitat.io
License: MIT
Platform: UNKNOWN
